<item id="14" name="" parent="12" title="" zoneName="BelowContent" templateKey="ImageAndText" state="16" created="09/22/2013 05:35:24" updated="04/12/2014 06:13:08" published="09/22/2013 05:35:50" expires="" sortOrder="-5" url="/ContentPages/Index?n2page=12&amp;n2item=14" visible="True" savedBy="admin" typeName="Dinamico.Models.ContentPart, ElixTech.V3" discriminator="ContentPart" versionIndex="1" ancestralTrail="/1/4/5/10/12/" alteredPermissions="0" childState="2"><details><detail name="ImageFirst" typeName="System.Boolean, mscorlib" meta="">False</detail><detail name="HiddenPhone" typeName="System.Boolean, mscorlib" meta="">False</detail><detail name="Image" typeName="System.String, mscorlib" meta="" encoded="True"><![CDATA[/upload/projects/photon_200.jpg]]></detail><detail name="Description" typeName="System.String, mscorlib" meta="" encoded="True"><![CDATA[&lt;h2&gt;Photon Mapping&lt;/h2&gt;

&lt;p&gt;As a student in CS224, we built upon Milton to implement photon mapping. Milton was implemented by Matt Jacobs and Travis Fischer, two other students from Brown CS, and it contains a scenegraph, ray tracer, and an implementation of Metropolis Light Transport (MLT).&lt;/p&gt;

&lt;h2&gt;High Performance Computing&lt;/h2&gt;

&lt;p&gt;We extended Polaris to work on a distributed computing cluster. Polaris compiles and runs on both Brown&amp;#39;&amp;#39;s Oscar HPC cluster (over 200 nodes) and the NICS Kraken cluster (over 9000 nodes) which is one of the most powerful supercomputers in the world. Polaris could be used to render extremely detailed scenes and high-resolution images by rendering a single frame in parallel. It can also be used to render video clips by rendering multiple frames in parallel.&lt;/p&gt;
]]></detail><detail name="VersionKey" typeName="System.String, mscorlib" meta="" encoded="True"><![CDATA[8cb67ee0-1e96-4d01-a74a-3171e6a21bd5]]></detail></details><detailCollections><collection name="TrackedLinks"><detail name="TrackedLinks" typeName="N2.Details.IMultipleValue, N2" meta="Image"><value key="Bool">False</value><value key="Int">0</value><value key="Link">0</value><value key="String" encoded="True"><![CDATA[/upload/projects/photon_200.jpg]]></value></detail></collection></detailCollections><children /><authorizations /><properties /></item>